pdfrenamer/StandardAbbreviations.txt
pdfrenamer/UserDefinedAbbreviations.txt
pdfrenamer/__init__.py
pdfrenamer/config.py
pdfrenamer/filename_creators.py
pdfrenamer/main.py
pdfrenamer/settings.ini
pdfrenamer/utils_registry.py
pdf_renamer-1.1.dist-info/METADATA
pdf_renamer-1.1.dist-info/WHEEL
pdf_renamer-1.1.dist-info/entry_points.txt
pdf_renamer-1.1.dist-info/top_level.txt
pdf_renamer-1.1.dist-info/RECORD
