Metadata-Version: 2.1
Name: pdf-renamer
Version: 1.1
Summary: A python library/command-line tool to automatically rename the pdf files of scientific publications by looking up the publication metadata on the web.
Home-page: https://github.com/MicheleCotrufo/pdf-renamer
Author: Michele Cotrufo
Author-email: michele.cotrufo@gmail.com
License: MIT
Platform: UNKNOWN
Requires-Dist: pdf2doi (>=1.6)
Requires-Dist: pdf2bib (>=1.2)
Requires-Dist: bibtexparser (>=1.2.0)
Requires-Dist: colorama
